geodesy/__init__.py
geodesy/sphere.cp37-win_amd64.pyd
geodesy/wgs84.cp37-win_amd64.pyd
geodesy-1.1.dist-info/METADATA
geodesy-1.1.dist-info/WHEEL
geodesy-1.1.dist-info/license.txt
geodesy-1.1.dist-info/top_level.txt
geodesy-1.1.dist-info/RECORD
