Metadata-Version: 2.1
Name: geodesy
Version: 1.1
Summary: A pragmatic and efficient geodesy toolkit
Home-page: https://github.com/xoolive/geodesy
Author: Xavier Olive
Author-email: xavier@xoolive.org
License: MIT
Platform: UNKNOWN
